[
  {
    "ContainingType": "TesteApiWeb.Controllers.AuthController",
    "Method": "EntrarAsync",
    "RelativePath": "api/Auth/Entrar",
    "HttpMethod": "POST",
    "IsController": true,
    "Order": 0,
    "Parameters": [
      {
        "Name": "loginDto",
        "Type": "TesteApiWeb.Models.AuthDTO\u002BLoginDTO",
        "IsRequired": true
      }
    ],
    "ReturnTypes": []
  },
  {
    "ContainingType": "TesteApiWeb.Controllers.AuthController",
    "Method": "RegistrarAsync",
    "RelativePath": "api/Auth/Registrar",
    "HttpMethod": "POST",
    "IsController": true,
    "Order": 0,
    "Parameters": [
      {
        "Name": "registerDTO",
        "Type": "TesteApiWeb.Models.AuthDTO\u002BRegisterDTOCreate",
        "IsRequired": true
      }
    ],
    "ReturnTypes": []
  },
  {
    "ContainingType": "TesteApiWeb.Controllers.CategoriasController",
    "Method": "ObterCategoriasAsync",
    "RelativePath": "api/Categorias",
    "HttpMethod": "GET",
    "IsController": true,
    "Order": 0,
    "Parameters": [],
    "ReturnTypes": []
  },
  {
    "ContainingType": "TesteApiWeb.Controllers.CategoriasController",
    "Method": "AdicionarCategoriaAsync",
    "RelativePath": "api/Categorias",
    "HttpMethod": "POST",
    "IsController": true,
    "Order": 0,
    "Parameters": [
      {
        "Name": "categoriaDTO",
        "Type": "DTOS.Categoria.CategoriaDTO\u002BCategoriaCreateDTO",
        "IsRequired": true
      }
    ],
    "ReturnTypes": []
  },
  {
    "ContainingType": "TesteApiWeb.Controllers.CategoriasController",
    "Method": "ObterCategoriaPorId",
    "RelativePath": "api/Categorias/{id}",
    "HttpMethod": "GET",
    "IsController": true,
    "Order": 0,
    "Parameters": [
      {
        "Name": "id",
        "Type": "System.Int32",
        "IsRequired": true
      }
    ],
    "ReturnTypes": []
  },
  {
    "ContainingType": "TesteApiWeb.Controllers.CategoriasController",
    "Method": "EditarCategoriaAsync",
    "RelativePath": "api/Categorias/{id}",
    "HttpMethod": "PUT",
    "IsController": true,
    "Order": 0,
    "Parameters": [
      {
        "Name": "id",
        "Type": "System.Int32",
        "IsRequired": true
      },
      {
        "Name": "categoriaDTO",
        "Type": "DTOS.Categoria.CategoriaDTO\u002BCategoriaUpdateDTO",
        "IsRequired": true
      }
    ],
    "ReturnTypes": []
  },
  {
    "ContainingType": "TesteApiWeb.Controllers.CategoriasController",
    "Method": "ExcluirCategoriaAsync",
    "RelativePath": "api/Categorias/{id}",
    "HttpMethod": "DELETE",
    "IsController": true,
    "Order": 0,
    "Parameters": [
      {
        "Name": "id",
        "Type": "System.Int32",
        "IsRequired": true
      }
    ],
    "ReturnTypes": []
  },
  {
    "ContainingType": "TesteApiWeb.Controllers.LivrosController",
    "Method": "ObterLivrosAsync",
    "RelativePath": "api/Livros",
    "HttpMethod": "GET",
    "IsController": true,
    "Order": 0,
    "Parameters": [],
    "ReturnTypes": []
  },
  {
    "ContainingType": "TesteApiWeb.Controllers.LivrosController",
    "Method": "CriarLivroAsync",
    "RelativePath": "api/Livros",
    "HttpMethod": "POST",
    "IsController": true,
    "Order": 0,
    "Parameters": [
      {
        "Name": "livroCreateEditDTO",
        "Type": "DTOS.Livro.LivroDTO\u002BLivroCreateDTO",
        "IsRequired": true
      }
    ],
    "ReturnTypes": []
  },
  {
    "ContainingType": "TesteApiWeb.Controllers.LivrosController",
    "Method": "ObterLivroPorId",
    "RelativePath": "api/Livros/{id}",
    "HttpMethod": "GET",
    "IsController": true,
    "Order": 0,
    "Parameters": [
      {
        "Name": "id",
        "Type": "System.Int32",
        "IsRequired": true
      }
    ],
    "ReturnTypes": []
  },
  {
    "ContainingType": "TesteApiWeb.Controllers.LivrosController",
    "Method": "EditarLivroAsync",
    "RelativePath": "api/Livros/{id}",
    "HttpMethod": "PUT",
    "IsController": true,
    "Order": 0,
    "Parameters": [
      {
        "Name": "id",
        "Type": "System.Int32",
        "IsRequired": true
      },
      {
        "Name": "livroDto",
        "Type": "DTOS.Livro.LivroDTO\u002BLivroEditDTO",
        "IsRequired": true
      }
    ],
    "ReturnTypes": []
  },
  {
    "ContainingType": "TesteApiWeb.Controllers.LivrosController",
    "Method": "ExcluirLivroAsync",
    "RelativePath": "api/Livros/{id}",
    "HttpMethod": "DELETE",
    "IsController": true,
    "Order": 0,
    "Parameters": [
      {
        "Name": "id",
        "Type": "System.Int32",
        "IsRequired": true
      }
    ],
    "ReturnTypes": []
  },
  {
    "ContainingType": "TesteApiWeb.Controllers.UsuariosController",
    "Method": "ObterUsuariosAsync",
    "RelativePath": "api/Usuarios",
    "HttpMethod": "GET",
    "IsController": true,
    "Order": 0,
    "Parameters": [],
    "ReturnTypes": []
  },
  {
    "ContainingType": "TesteApiWeb.Controllers.UsuariosController",
    "Method": "ObterUsuarioPorIdAsync",
    "RelativePath": "api/Usuarios/{id}",
    "HttpMethod": "GET",
    "IsController": true,
    "Order": 0,
    "Parameters": [
      {
        "Name": "id",
        "Type": "System.String",
        "IsRequired": true
      }
    ],
    "ReturnTypes": []
  },
  {
    "ContainingType": "TesteApiWeb.Controllers.UsuariosController",
    "Method": "EditarUsuarioAsync",
    "RelativePath": "api/Usuarios/{id}",
    "HttpMethod": "PUT",
    "IsController": true,
    "Order": 0,
    "Parameters": [
      {
        "Name": "id",
        "Type": "System.String",
        "IsRequired": true
      },
      {
        "Name": "usuarioDTO",
        "Type": "DTOS.Usuario.UsuarioDTO\u002BUsuarioDTOEdit",
        "IsRequired": true
      }
    ],
    "ReturnTypes": []
  },
  {
    "ContainingType": "TesteApiWeb.Controllers.UsuariosController",
    "Method": "ExcluirUsuarioAsync",
    "RelativePath": "api/Usuarios/{id}",
    "HttpMethod": "DELETE",
    "IsController": true,
    "Order": 0,
    "Parameters": [
      {
        "Name": "id",
        "Type": "System.String",
        "IsRequired": true
      }
    ],
    "ReturnTypes": []
  }
]